CHANGES.md
MANIFEST.in
README.md
setup.py
webcheck/__init__.py
webcheck/__main__.py
webcheck/webcheck.py
webcheck.egg-info/PKG-INFO
webcheck.egg-info/SOURCES.txt
webcheck.egg-info/dependency_links.txt
webcheck.egg-info/not-zip-safe
webcheck.egg-info/requires.txt
webcheck.egg-info/top_level.txt