Metadata-Version: 2.1
Name: webcheck
Version: 1.2.0
Summary: A Web Site check tool.
Home-page: https://github.com/sintrb/webcheck/
Author: trb
Author-email: sintrb@gmail.com
License: UNKNOWN
Keywords: webcheck,HTTP,HTTPS,SSL
Platform: UNKNOWN
